tkx/__init__.py
tkx/constants.py
tkx/core.py
tkx/element.py
tkx/error.py
tkx/stylesheet.py
tkx/window.py
tkx-0.1.1.dist-info/LICENSE
tkx-0.1.1.dist-info/WHEEL
tkx-0.1.1.dist-info/METADATA
tkx-0.1.1.dist-info/RECORD
