Metadata-Version: 2.1
Name: tkx
Version: 0.1.1
Summary: 
Author: Hunter Logan
Author-email: _@piccoloser.com
Requires-Python: >=3.10,<4.0
Classifier: Programming Language :: Python :: 3
Classifier: Programming Language :: Python :: 3.10
Classifier: Programming Language :: Python :: 3.11
